pyrvt/__init__.py
pyrvt/_version.py
pyrvt/motions.py
pyrvt/peak_calculators.py
pyrvt/runner.py
pyrvt/tools.py
pyrvt/data/cena_bt12_trms4osc.pars.gz
pyrvt/data/cena_bt15_trms4osc.pars.gz
pyrvt/data/sea22-site_amp.csv.gz
pyrvt/data/wna_bt12_trms4osc.pars.gz
pyrvt/data/wna_bt15_trms4osc.pars.gz
pyrvt-0.8.1.dist-info/licenses/AUTHORS.md
pyrvt-0.8.1.dist-info/licenses/LICENSE
pyrvt-0.8.1.dist-info/METADATA
pyrvt-0.8.1.dist-info/WHEEL
pyrvt-0.8.1.dist-info/entry_points.txt
pyrvt-0.8.1.dist-info/top_level.txt
pyrvt-0.8.1.dist-info/RECORD
