Metadata-Version: 2.4
Name: pyRVT
Version: 0.8.1
Summary: Random vibration theory for earthquake ground motions.
Author-email: Albert Kottke <albert.kottke@gmail.com>
License: MIT
Project-URL: Homepage, https://github.com/arkottke/pyrvt
Project-URL: Documentation, https://pyrvt.readthedocs.io
Requires-Python: >=3.10
License-File: LICENSE
License-File: AUTHORS.md
Requires-Dist: numpy
Requires-Dist: numba
Requires-Dist: scipy
Requires-Dist: pyexcel
Requires-Dist: pyexcel-io
Requires-Dist: pyexcel-xlsx
Provides-Extra: test
Requires-Dist: coverage[toml]; extra == "test"
Requires-Dist: pandas; extra == "test"
Requires-Dist: pytest; extra == "test"
Requires-Dist: pytest-cov; extra == "test"
Requires-Dist: pystrata; extra == "test"
Requires-Dist: pykooh; extra == "test"
Requires-Dist: matplotlib; extra == "test"
Requires-Dist: tomli; python_version < "3.11" and extra == "test"
Provides-Extra: docs
Requires-Dist: sphinx; extra == "docs"
Requires-Dist: furo; extra == "docs"
Requires-Dist: sphinx-copybutton; extra == "docs"
Requires-Dist: sphinx-design; extra == "docs"
Requires-Dist: sphinxcontrib-bibtex; extra == "docs"
Requires-Dist: sphinxext-opengraph; extra == "docs"
Requires-Dist: sphinx-autobuild; extra == "docs"
Requires-Dist: matplotlib; extra == "docs"
Requires-Dist: myst-parser; extra == "docs"
Requires-Dist: nbsphinx; extra == "docs"
Requires-Dist: ipython; extra == "docs"
Requires-Dist: linkify-it-py; extra == "docs"
Provides-Extra: style
Requires-Dist: black[colorama,jupyter]; extra == "style"
Requires-Dist: ruff; extra == "style"
Dynamic: license-file
